botol4/__init__.py
botol4/dammit.py
botol4/diagnose.py
botol4/element.py
botol4/formatter.py
botol4/testing.py
botol4/builder/__init__.py
botol4/builder/_html5lib.py
botol4/builder/_htmlparser.py
botol4/builder/_lxml.py
botol4/tests/__init__.py
botol4/tests/test_builder_registry.py
botol4/tests/test_docs.py
botol4/tests/test_html5lib.py
botol4/tests/test_htmlparser.py
botol4/tests/test_lxml.py
botol4/tests/test_soup.py
botol4/tests/test_tree.py
botol4-1.0.dist-info/LICENSE
botol4-1.0.dist-info/METADATA
botol4-1.0.dist-info/WHEEL
botol4-1.0.dist-info/top_level.txt
botol4-1.0.dist-info/RECORD
